README.md
setup.py
geoname_enrichment/__init__.py
geoname_enrichment/csv_logger.py
geoname_enrichment/geoname_enrichment.py
geoname_enrichment/utils.py
geoname_enrichment.egg-info/PKG-INFO
geoname_enrichment.egg-info/SOURCES.txt
geoname_enrichment.egg-info/dependency_links.txt
geoname_enrichment.egg-info/top_level.txt