Metadata-Version: 2.1
Name: geoname-enrichment
Version: 0.1.0
Summary: A Python script to enrich placenames in a CSV file with geoname data from a custom API.
Home-page: https://github.com/metabelgica/geoname-enrichment
Author: Sven Lieber
Author-email: Sven.Lieber@kbr.be
License: MIT
Keywords: geonames CSV
Platform: UNKNOWN
